oxylabs_mcp/__init__.py
oxylabs_mcp/config.py
oxylabs_mcp/exceptions.py
oxylabs_mcp/url_params.py
oxylabs_mcp/utils.py
oxylabs_mcp/tools/__init__.py
oxylabs_mcp/tools/ai_studio.py
oxylabs_mcp/tools/misc.py
oxylabs_mcp/tools/scraper.py
oxylabs_mcp-0.7.5.dist-info/METADATA
oxylabs_mcp-0.7.5.dist-info/WHEEL
oxylabs_mcp-0.7.5.dist-info/entry_points.txt
oxylabs_mcp-0.7.5.dist-info/licenses/LICENSE
oxylabs_mcp-0.7.5.dist-info/RECORD
