Metadata-Version: 2.4
Name: oxylabs-mcp
Version: 0.7.5
Summary: Oxylabs MCP server
Project-URL: Homepage, https://github.com/oxylabs/oxylabs-mcp
Project-URL: Repository, https://github.com/oxylabs/oxylabs-mcp
Author-email: Augis Braziunas <augis.braziunas@oxylabs.io>, Rostyslav Borovyk <rostyslav.borovyk@oxylabs.io>
License-Expression: MIT
License-File: LICENSE
Classifier: Development Status :: 4 - Beta
Classifier: Operating System :: OS Independent
Classifier: Programming Language :: Python :: 3
Classifier: Programming Language :: Python :: 3.12
Classifier: Programming Language :: Python :: 3.13
Requires-Python: >=3.12
Requires-Dist: fastmcp>=2.11.3
Requires-Dist: httpx>=0.28.1
Requires-Dist: lxml-html-clean>=0.4.1
Requires-Dist: lxml<6,>=5.3.0
Requires-Dist: markdownify==0.14.1
Requires-Dist: oxylabs-ai-studio>=0.2.20
Requires-Dist: pydantic-settings>=2.8.1
Requires-Dist: pydantic>=2.10.5
Requires-Dist: smithery>=0.1.25
